bnc_scraper/__init__.py
bnc_scraper/downloader.py
bnc_scraper/scraper.py
bnc_scraper/types.py
bnc_scraper/utils.py
test/__init__.py
test/test_downloader.py
bnc_scraper-0.0.1.dist-info/LICENSE
bnc_scraper-0.0.1.dist-info/METADATA
bnc_scraper-0.0.1.dist-info/WHEEL
bnc_scraper-0.0.1.dist-info/top_level.txt
bnc_scraper-0.0.1.dist-info/RECORD
